{
  "resolvedId": "/Users/jameslajom/Documents/git/boxmaker-ui/pages/index.vue?vue&type=style&index=0&lang.css?inline&used",
  "transforms": [
    {
      "name": "vite:vue",
      "result": "\n.ui.dimmer.active {\n    position: fixed;\n    min-height: 100vh;\n    height: 100vh;\n    z-index: 5;\n    max-width:760px;\n}\n",
      "start": 1702950701138,
      "end": 1702950701138,
      "sourcemaps": {
        "version": 3,
        "sources": [
          "/Users/jameslajom/Documents/git/boxmaker-ui/pages/index.vue"
        ],
        "names": [],
        "mappings": ";AAuDA,CAAC,CAAC,CAAC,CAAC,CAAC,CAAC,CAAC,CAAC,CAAC,CAAC,CAAC,CAAC,CAAC,CAAC,CAAC,CAAC,EAAE;IACd,CAAC,CAAC,CAAC,CAAC,CAAC,CAAC,CAAC,CAAC,EAAE,CAAC,CAAC,CAAC,CAAC,CAAC;IACf,CAAC,CAAC,CAAC,CAAC,CAAC,CAAC,CAAC,CAAC,CAAC,CAAC,EAAE,CAAC,CAAC,CAAC,CAAC,CAAC;IACjB,CAAC,CAAC,CAAC,CAAC,CAAC,CAAC,EAAE,CAAC,CAAC,CAAC,CAAC,CAAC;IACb,CAAC,CAAC,CAAC,CAAC,CAAC,CAAC,CAAC,EAAE,CAAC;IACV,CAAC,CAAC,CAAC,CAAC,CAAC,CAAC,CAAC,CAAC,CAAC,CAAC,CAAC,CAAC,CAAC,CAAC,CAAC;AACnB",
        "file": "/Users/jameslajom/Documents/git/boxmaker-ui/pages/index.vue",
        "sourceRoot": "",
        "sourcesContent": [
          "<template>\n    <div class=\"ui container\">\n        <ElFlyout :isOpen=\"flyout\" @isClosed=\"closeFlyout\" :box=\"selected_box?selected_box:{}\"></ElFlyout>\n\n\n        <!-- <div class=\"ui segment\">\n            <div class=\"ui\" style=\"width:100%;text-align:right;\">\n                <div style=\"text-align:right;\" class=\"ui labeled button\" tabindex=\"0\">\n                    <div class=\"ui yellow button\">\n                        <i class=\"coins icon\"></i> + Coins\n                    </div>\n                    <a class=\"ui basic yellow left pointing label\">\n                        1,048\n                    </a>\n                </div>\n            </div>\n        </div> -->\n        <div class=\"ui segment\">\n            <BoxTags @selectedTagsId=\"handleSelectedTags\"></BoxTags>\n            <BoxTray :selectedTags=\"selectedTags\" @selected=\"handleSelectedBox\"></BoxTray>\n        </div>\n        <div class=\"ui dimmer fluid\" :class=\"flyout ? 'active' : ''\"></div>\n    </div>\n</template>\n\n\n<script>\nexport default {\n    data() {\n        return {\n            flyout:false,\n            selectedTags: [],\n            selected_box: null,\n        }\n    },\n    methods: {\n        handleSelectedTags(v) {\n            this.selectedTags = v;\n        },\n        handleSelectedBox(v){\n            // alert(`index page selected_box = ${v}`)\n            // console.log(v);\n            this.selected_box = v;\n            this.flyout = true;\n        },\n        closeFlyout(){\n            this.selected_box=null;\n            this.flyout = false;            \n        }\n    }\n}\n\n</script>\n\n<style>\n.ui.dimmer.active {\n    position: fixed;\n    min-height: 100vh;\n    height: 100vh;\n    z-index: 5;\n    max-width:760px;\n}\n</style>"
        ]
      }
    },
    {
      "name": "nuxt:layer-aliasing",
      "start": 1702950701138,
      "end": 1702950701138,
      "order": "pre"
    },
    {
      "name": "nuxt:layer-aliasing",
      "start": 1702950701138,
      "end": 1702950701138,
      "order": "pre"
    },
    {
      "name": "nuxt:server-devonly:transform",
      "start": 1702950701138,
      "end": 1702950701138,
      "order": "pre"
    },
    {
      "name": "nuxt:server-devonly:transform",
      "start": 1702950701138,
      "end": 1702950701138,
      "order": "pre"
    },
    {
      "name": "nuxt:client-fallback-auto-id",
      "start": 1702950701138,
      "end": 1702950701138,
      "order": "pre"
    },
    {
      "name": "vite:css",
      "result": ".ui.dimmer.active{height:100vh;max-width:760px;min-height:100vh;position:fixed;z-index:5}",
      "start": 1702950701139,
      "end": 1702950701167,
      "order": "normal",
      "sourcemaps": {
        "file": "/Users/jameslajom/Documents/git/boxmaker-ui/pages/index.vue",
        "mappings": "AACA,kBAGI,YAAa,CAEb,eAAe,CAHf,gBAAiB,CADjB,cAAe,CAGf,SAEJ",
        "names": [],
        "sources": [
          "/Users/jameslajom/Documents/git/boxmaker-ui/pages/index.vue"
        ],
        "sourcesContent": [
          "\n.ui.dimmer.active {\n    position: fixed;\n    min-height: 100vh;\n    height: 100vh;\n    z-index: 5;\n    max-width:760px;\n}\n"
        ],
        "version": 3
      }
    },
    {
      "name": "vite:esbuild",
      "start": 1702950701168,
      "end": 1702950701168,
      "order": "normal"
    },
    {
      "name": "vite:json",
      "start": 1702950701168,
      "end": 1702950701168,
      "order": "normal"
    },
    {
      "name": "vite:worker",
      "start": 1702950701168,
      "end": 1702950701168,
      "order": "normal"
    },
    {
      "name": "vite:vue",
      "result": ".ui.dimmer.active{height:100vh;max-width:760px;min-height:100vh;position:fixed;z-index:5}",
      "start": 1702950701168,
      "end": 1702950701169,
      "order": "normal",
      "sourcemaps": {
        "file": "/Users/jameslajom/Documents/git/boxmaker-ui/pages/index.vue",
        "mappings": "AAAA,kBAAkB,YAAY,CAAC,eAAe,CAAC,gBAAgB,CAAC,cAAc,CAAC,SAAS",
        "names": [],
        "sources": [
          "/Users/jameslajom/Documents/git/boxmaker-ui/pages/index.vue"
        ],
        "sourcesContent": [
          null
        ],
        "version": 3
      }
    },
    {
      "name": "vite:vue-jsx",
      "start": 1702950701169,
      "end": 1702950701169,
      "order": "normal"
    },
    {
      "name": "replace",
      "start": 1702950701169,
      "end": 1702950701169,
      "order": "normal"
    },
    {
      "name": "replace",
      "start": 1702950701169,
      "end": 1702950701169,
      "order": "normal"
    },
    {
      "name": "nuxt:remove-plugin-metadata",
      "start": 1702950701169,
      "end": 1702950701169,
      "order": "normal"
    },
    {
      "name": "nuxt:remove-plugin-metadata",
      "start": 1702950701169,
      "end": 1702950701169,
      "order": "normal"
    },
    {
      "name": "replace",
      "start": 1702950701169,
      "end": 1702950701169,
      "order": "normal"
    },
    {
      "name": "nuxt:components:imports",
      "start": 1702950701170,
      "end": 1702950701170,
      "order": "normal"
    },
    {
      "name": "replace",
      "start": 1702950701170,
      "end": 1702950701170,
      "order": "normal"
    },
    {
      "name": "ssr-styles",
      "start": 1702950701170,
      "end": 1702950701170,
      "order": "normal"
    },
    {
      "name": "vite:define",
      "start": 1702950701171,
      "end": 1702950701171,
      "order": "normal"
    },
    {
      "name": "vite:css-post",
      "result": "export default \".ui.dimmer.active{height:100vh;max-width:760px;min-height:100vh;position:fixed;z-index:5}\"",
      "start": 1702950701174,
      "end": 1702950701174,
      "order": "normal",
      "sourcemaps": {
        "mappings": ""
      }
    },
    {
      "name": "vite:build-html",
      "start": 1702950701174,
      "end": 1702950701174,
      "order": "normal"
    },
    {
      "name": "vite:worker-import-meta-url",
      "start": 1702950701174,
      "end": 1702950701174,
      "order": "normal"
    },
    {
      "name": "vite:asset-import-meta-url",
      "start": 1702950701174,
      "end": 1702950701174,
      "order": "normal"
    },
    {
      "name": "commonjs",
      "start": 1702950701174,
      "end": 1702950701174,
      "order": "normal"
    },
    {
      "name": "vite:dynamic-import-vars",
      "start": 1702950701175,
      "end": 1702950701175,
      "order": "normal"
    },
    {
      "name": "vite:import-glob",
      "start": 1702950701175,
      "end": 1702950701175,
      "order": "normal"
    },
    {
      "name": "nuxt:composable-keys",
      "start": 1702950701175,
      "end": 1702950701175,
      "order": "post"
    },
    {
      "name": "nuxt:composable-keys",
      "start": 1702950701175,
      "end": 1702950701175,
      "order": "post"
    },
    {
      "name": "nuxt:imports-transform",
      "start": 1702950701175,
      "end": 1702950701175,
      "order": "post"
    },
    {
      "name": "nuxt:imports-transform",
      "start": 1702950701175,
      "end": 1702950701175,
      "order": "post"
    },
    {
      "name": "unctx:transform",
      "start": 1702950701175,
      "end": 1702950701175,
      "order": "post"
    },
    {
      "name": "unctx:transform",
      "start": 1702950701175,
      "end": 1702950701175,
      "order": "post"
    },
    {
      "name": "nuxt:pages-macros-transform",
      "start": 1702950701175,
      "end": 1702950701176,
      "order": "post"
    },
    {
      "name": "nuxt:pages-macros-transform",
      "start": 1702950701175,
      "end": 1702950701176,
      "order": "post"
    },
    {
      "name": "nuxt:tree-shake-template",
      "start": 1702950701176,
      "end": 1702950701176,
      "order": "post"
    },
    {
      "name": "nuxt:components-loader",
      "start": 1702950701176,
      "end": 1702950701176,
      "order": "post"
    },
    {
      "name": "nuxt:tree-shake-composables:transform",
      "start": 1702950701176,
      "end": 1702950701176,
      "order": "post"
    },
    {
      "name": "vite:build-import-analysis",
      "start": 1702950701176,
      "end": 1702950701176,
      "order": "normal"
    },
    {
      "name": "vite:reporter",
      "start": 1702950701176,
      "end": 1702950701176,
      "order": "normal"
    }
  ]
}
